paymentsgate/__init__.py
paymentsgate/cache.py
paymentsgate/client.py
paymentsgate/enums.py
paymentsgate/exceptions.py
paymentsgate/logger.py
paymentsgate/mappers.py
paymentsgate/models.py
paymentsgate/signature.py
paymentsgate/tokens.py
paymentsgate/transport.py
paymentsgate/types.py
paymentsgate-1.5.14.dist-info/LICENSE
paymentsgate-1.5.14.dist-info/WHEEL
paymentsgate-1.5.14.dist-info/METADATA
paymentsgate-1.5.14.dist-info/RECORD
