Metadata-Version: 2.1
Name: paymentsgate
Version: 1.5.14
Summary: PaymentsGate's Python SDK for REST API
Home-page: https://github.com/paymentsgate/python-secure-api
License: MIT
Keywords: paymentsgate,payments,sdk,api
Author: PaymentsGate
Requires-Python: >=3.10,<4.0
Classifier: Development Status :: 5 - Production/Stable
Classifier: Intended Audience :: Developers
Classifier: License :: OSI Approved :: MIT License
Classifier: Programming Language :: Python :: 3
Classifier: Programming Language :: Python :: 3.10
Classifier: Topic :: Software Development :: Libraries :: Python Modules
Requires-Dist: cryptography (>=44.0.2,<45.0.0)
Requires-Dist: httpx (>=0.28.1,<0.29.0)
Requires-Dist: jwt (>=1.3.1,<2.0.0)
Requires-Dist: pydantic (>=2.8.2,<3.0.0)
Requires-Dist: ruff (>=0.11.7,<0.12.0)
Requires-Dist: tomli (>=2.0.1,<3.0.0)
Project-URL: Documentation, https://github.com/paymentsgate/python-secure-api
Project-URL: Repository, https://github.com/paymentsgate/python-secure-api
